kageku/__init__.py
kageku/action.py
kageku/board.py
kageku/consts.py
kageku/flags.py
Kageku-1.1.2.dist-info/LICENSE
Kageku-1.1.2.dist-info/METADATA
Kageku-1.1.2.dist-info/WHEEL
Kageku-1.1.2.dist-info/top_level.txt
Kageku-1.1.2.dist-info/RECORD
