Metadata-Version: 2.1
Name: Kageku
Version: 1.1.2
Summary: Implementation of a chess based game created by me and some friends for an RPG we play
Home-page: https://github.com/lucaspellegrinelli/kageku
Author: Lucas Pellegrinelli
Author-email: lucas.pellegrinelli@hotmail.com
License: MIT License
Platform: UNKNOWN
